arcade_figma_api/__init__.py
arcade_figma_api/tools/__init__.py
arcade_figma_api/tools/request_body_schemas.py
arcade_figma_api/wrapper_tools/AddCommentToFigmaFile.json
arcade_figma_api/wrapper_tools/AddFigmaCommentReaction.json
arcade_figma_api/wrapper_tools/BulkUpdateFigmaDevResources.json
arcade_figma_api/wrapper_tools/CreateBulkDevResources.json
arcade_figma_api/wrapper_tools/CreateFigmaWebhook.json
arcade_figma_api/wrapper_tools/DeleteDevResource.json
arcade_figma_api/wrapper_tools/DeleteFigmaComment.json
arcade_figma_api/wrapper_tools/DeleteFigmaWebhook.json
arcade_figma_api/wrapper_tools/DeleteMyCommentReaction.json
arcade_figma_api/wrapper_tools/FetchCommentReactions.json
arcade_figma_api/wrapper_tools/FetchComponentUsageData.json
arcade_figma_api/wrapper_tools/FetchFigmaFile.json
arcade_figma_api/wrapper_tools/FetchFileVersionHistory.json
arcade_figma_api/wrapper_tools/FetchImageFillLinks.json
arcade_figma_api/wrapper_tools/FetchLibraryAnalyticsVariableActions.json
arcade_figma_api/wrapper_tools/FigmaGetTeamProjects.json
arcade_figma_api/wrapper_tools/GetDevResources.json
arcade_figma_api/wrapper_tools/GetFigmaComponentMetadata.json
arcade_figma_api/wrapper_tools/GetFigmaComponentSet.json
arcade_figma_api/wrapper_tools/GetFigmaFileComments.json
arcade_figma_api/wrapper_tools/GetFigmaFileComponents.json
arcade_figma_api/wrapper_tools/GetFigmaFileNodes.json
arcade_figma_api/wrapper_tools/GetFigmaProjectFiles.json
arcade_figma_api/wrapper_tools/GetFigmaWebhook.json
arcade_figma_api/wrapper_tools/GetFigmaWebhooks.json
arcade_figma_api/wrapper_tools/GetFileMetadata.json
arcade_figma_api/wrapper_tools/GetLibraryAnalyticsComponentActions.json
arcade_figma_api/wrapper_tools/GetLibraryAnalyticsVariableUsages.json
arcade_figma_api/wrapper_tools/GetLibraryStyleActions.json
arcade_figma_api/wrapper_tools/GetLibraryStyleUsageData.json
arcade_figma_api/wrapper_tools/GetPublishedComponentSets.json
arcade_figma_api/wrapper_tools/GetPublishedStylesFromFile.json
arcade_figma_api-1.0.0.dist-info/METADATA
arcade_figma_api-1.0.0.dist-info/WHEEL
arcade_figma_api-1.0.0.dist-info/entry_points.txt
arcade_figma_api-1.0.0.dist-info/licenses/LICENSE
arcade_figma_api-1.0.0.dist-info/RECORD
